dlutils/__init__.py
dlutils/_version.py
dlutils/data/__init__.py
dlutils/data/fake.py
dlutils/losses/__init__.py
dlutils/losses/adversarial.py
dlutils/losses/boundary_equilibrium.py
dlutils/losses/boundary_seeking.py
dlutils/losses/discriminator_margin.py
dlutils/losses/distance.py
dlutils/losses/focal.py
dlutils/losses/gradient_penalty.py
dlutils/losses/iterative_discriminator.py
dlutils/losses/pull_away.py
dlutils/losses/soft_dice.py
dlutils/losses/tversky.py
dlutils/losses/wasserstein_divergence.py
dlutils/metrics/__init__.py
dlutils/metrics/dice.py
dlutils/models/__init__.py
dlutils/models/alexnet.py
dlutils/models/densenet.py
dlutils/models/mobilenet.py
dlutils/models/nd.py
dlutils/models/resnet.py
dlutils/models/resnext.py
dlutils/models/seresnet.py
dlutils/models/seresnext.py
dlutils/models/unet.py
dlutils/models/vgg.py
dlutils/models/gans/__init__.py
dlutils/models/gans/utils.py
dlutils/models/gans/adversarial_autoencoder/__init__.py
dlutils/models/gans/adversarial_autoencoder/aae.py
dlutils/models/gans/adversarial_autoencoder/models.py
dlutils/models/gans/auxiliary_classifier/__init__.py
dlutils/models/gans/auxiliary_classifier/acgan.py
dlutils/models/gans/auxiliary_classifier/models.py
dlutils/models/gans/bicycle/__init__.py
dlutils/models/gans/bicycle/bicycle_gan.py
dlutils/models/gans/bicycle/models.py
dlutils/models/gans/boundary_equilibrium/__init__.py
dlutils/models/gans/boundary_equilibrium/began.py
dlutils/models/gans/boundary_equilibrium/models.py
dlutils/models/gans/boundary_seeking/__init__.py
dlutils/models/gans/boundary_seeking/bs_gan.py
dlutils/models/gans/boundary_seeking/models.py
dlutils/models/gans/conditional/__init__.py
dlutils/models/gans/conditional/conditional_gan.py
dlutils/models/gans/conditional/models.py
dlutils/models/gans/context_conditional/__init__.py
dlutils/models/gans/context_conditional/context_cond_gan.py
dlutils/models/gans/context_conditional/models.py
dlutils/models/gans/context_encoder/__init__.py
deep_learning_utils-0.0.1rc3.dist-info/LICENSE
deep_learning_utils-0.0.1rc3.dist-info/METADATA
deep_learning_utils-0.0.1rc3.dist-info/WHEEL
deep_learning_utils-0.0.1rc3.dist-info/top_level.txt
deep_learning_utils-0.0.1rc3.dist-info/RECORD
