Metadata-Version: 2.1
Name: deep-learning-utils
Version: 0.0.1rc3
Summary: UNKNOWN
Home-page: UNKNOWN
Author: Justus Schock
Maintainer: Justus Schock
Maintainer-email: justus.schock@rwth-aachen.de
License: MIT
Platform: UNKNOWN
Requires-Python: >=3.7
Requires-Dist: torch
Requires-Dist: rising
Requires-Dist: tqdm
Requires-Dist: tensorboard
Requires-Dist: hydra-core
Requires-Dist: omegaconf
Requires-Dist: scipy
